sxm_viewer/__init__.py
sxm_viewer/icon.png
sxm_viewer/main.py
sxm_viewer-0.31.dist-info/METADATA
sxm_viewer-0.31.dist-info/WHEEL
sxm_viewer-0.31.dist-info/entry_points.txt
sxm_viewer-0.31.dist-info/top_level.txt
sxm_viewer-0.31.dist-info/RECORD
