Metadata-Version: 2.1
Name: sxm-viewer
Version: 0.31
Summary: a PyQt5 based tool for inspecting *.sxm files and save them as figures swiftly.
Home-page: https://github.com/CoccaGuo/sxm-viewer
Author: Cocca Guo
Author-email: guojiadong@bnu.edu.cn
License: UNKNOWN
Platform: UNKNOWN
Classifier: Programming Language :: Python :: 3
Classifier: Operating System :: OS Independent
Requires-Python: >=3
Requires-Dist: numpy
Requires-Dist: pySPM
Requires-Dist: PyQt5
Requires-Dist: matplotlib
Requires-Dist: opencv-python
